lowmq_client/__init__.py
lowmq_client/client.py
lowmq_client/exceptions.py
lowmq_client/lowmq_client.py
lowmq_client/models.py
lowmq_client/py.typed
lowmq_client-1.0.0.dist-info/licenses/LICENSE
lowmq_client-1.0.0.dist-info/METADATA
lowmq_client-1.0.0.dist-info/WHEEL
lowmq_client-1.0.0.dist-info/top_level.txt
lowmq_client-1.0.0.dist-info/RECORD
