Metadata-Version: 2.4
Name: lowmq-client
Version: 1.0.0
Summary: Python asynchronous client for interacting with LowMQ
Author: AI-Stratov
License: MIT
Project-URL: Homepage, https://github.com/AI-Stratov/lowmq-python-client
Project-URL: Repository, https://github.com/AI-Stratov/lowmq-python-client
Project-URL: Issues, https://github.com/AI-Stratov/lowmq-python-client/issues
Project-URL: LowMQ Server, https://github.com/farawayCC/lowmq
Keywords: lowmq,message-queue,asyncio,aiohttp,client,pydantic
Classifier: Programming Language :: Python :: 3
Classifier: Programming Language :: Python :: 3 :: Only
Classifier: Programming Language :: Python :: 3.9
Classifier: Programming Language :: Python :: 3.10
Classifier: Programming Language :: Python :: 3.11
Classifier: Programming Language :: Python :: 3.12
Classifier: Typing :: Typed
Classifier: License :: OSI Approved :: MIT License
Classifier: Operating System :: OS Independent
Classifier: Framework :: AsyncIO
Requires-Python: >=3.9
License-File: LICENSE
Requires-Dist: pydantic>=2.6.4
Requires-Dist: aiohttp>=3.9.3
Provides-Extra: dev
Requires-Dist: ruff>=0.4.0; extra == "dev"
Requires-Dist: mypy>=1.8.0; extra == "dev"
Requires-Dist: pre-commit>=3.0.4; extra == "dev"
Requires-Dist: coverage>=5.3; extra == "dev"
Requires-Dist: uv>=0.2.0; extra == "dev"
Dynamic: license-file
